actions/core/__init__.py
actions/core/_compat.py
actions/core/_process.py
actions/core/command.py
actions/core/core.py
actions/core/file_command.py
actions/core/oidc_utils.py
actions/core/path_utils.py
actions/core/summary.py
actions/core/utils.py
actions_python_core-0.1.3.dist-info/METADATA
actions_python_core-0.1.3.dist-info/WHEEL
actions_python_core-0.1.3.dist-info/RECORD
