Metadata-Version: 2.1
Name: actions-python-core
Version: 0.1.3
Summary: Actions core lib
Project-URL: Homepage, https://github.com/actions-python/toolkit
Author-email: sudosubin <sudosubin@gmail.com>
License-Expression: MIT
Keywords: action,ci,github
Classifier: Development Status :: 2 - Pre-Alpha
Classifier: Environment :: Console
Classifier: Intended Audience :: Developers
Classifier: License :: OSI Approved :: MIT License
Classifier: Operating System :: OS Independent
Classifier: Programming Language :: Python
Classifier: Programming Language :: Python :: 3 :: Only
Classifier: Programming Language :: Python :: 3.9
Classifier: Programming Language :: Python :: 3.10
Classifier: Programming Language :: Python :: 3.11
Classifier: Programming Language :: Python :: 3.12
Classifier: Topic :: Software Development :: Libraries :: Python Modules
Classifier: Typing :: Typed
Requires-Python: >=3.9
Requires-Dist: aiofiles>=23.1
Requires-Dist: httpx<1.0.0,>=0.23
Requires-Dist: typing-extensions>=4.6; python_version < '3.11'
